common_lib-0.1.3.dist-info/DESCRIPTION.rst
common_lib-0.1.3.dist-info/METADATA
common_lib-0.1.3.dist-info/RECORD
common_lib-0.1.3.dist-info/WHEEL
common_lib-0.1.3.dist-info/metadata.json
common_lib-0.1.3.dist-info/top_level.txt
yr_math/__init__.py
yr_math/mymath.py
yr_math/test_mymath.py
