Metadata-Version: 1.0
Name: common-lib
Version: 0.1.3
Summary: common lib example
Home-page: UNKNOWN
Author: oren razon
Author-email: oren.razon@myyellowroad.com
License: UNKNOWN
Keywords: sample setuptools development
Platform: UNKNOWN
